{
	"_about": {
		"source": "Schmader, Whitehead, and Wysocki",
		"description": "Original list of gendered words",
		"creation": "2015-03-17"
	},
	"female": ["hardworking", "conscientious", "depend\\w*",  "dressing", "dress", "dedicate", "careful", "pretty", "effort\\w*", "assiduous", "beautiful", "responsib\\w*", "methodical", "industrious", "sweet", "obedient", "disciplined", "teach", "instruct", "pretty", "communal", "mentor", "supervis\\w*", "adviser", "lady", "child", "cute", "citizen", "woman",  "rapport", "smile", "caring","lovely", "linent"],
	"male": ["excellen\\w*", "superb", "outstanding", "unique", "exceptional", "unparalleled", "\\w{2,}est(\\W|$)", "best", "most", "wonderful", "terrific\\w*", "fabulous", "magnificent", "remarkable", "extraordinar\\w*", "amazing", "supreme\\w*", "unmatched", "talent\\w*", "intell\\w*", "smart\\w*", "skill\\w*", "ability", "genius", "brilliant\\w*", "bright\\w*", "brain\\w*", "aptitude", "gift\\w*", "capacity", "propensity", "innate", "flair", "knack", "clever\\w*", "expert\\w*", "proficient\\w*", "capable", "adept\\w*", "able", "competent", "natural\\w*", "inherent\\w*", "instinct\\w*", "adroit\\w*", "creative\\w*", "insight\\w*", "analytical", "research\\w*", "data", "study", "studies", "experiment\\w*", "scholarship", "result\\w*", "^test\\w*", "finding\\w*", "publication\\w*", "publish\\w*", "vita\\w*", "method\\w*", "scien\\w*", "grant\\w*", "fund\\w*", "manuscript\\w*", "project\\w*", "journal\\w*", "theor\\w*", "discover\\w*", "contribution\\w*"]
}